bookmarkapp/__init__.py
bookmarkapp/apps.py
bookmarkapp/static/admin/js/bookmark-app.js
bookmarkapp/templates/admin/app_list.html
bookmarkapp/templates/admin/bookmarks.html
django_app_bookmarker-0.5.dist-info/METADATA
django_app_bookmarker-0.5.dist-info/WHEEL
django_app_bookmarker-0.5.dist-info/top_level.txt
django_app_bookmarker-0.5.dist-info/RECORD
